README.md
setup.cfg
setup.py
openapi_client/__init__.py
openapi_client/api_client.py
openapi_client/configuration.py
openapi_client/exceptions.py
openapi_client/rest.py
openapi_client/schemas.py
openapi_client/apis/__init__.py
openapi_client/apis/path_to_api.py
openapi_client/apis/tag_to_api.py
openapi_client/apis/paths/__init__.py
openapi_client/apis/paths/auth_activate.py
openapi_client/apis/paths/auth_extend_trial.py
openapi_client/apis/paths/auth_keygen.py
openapi_client/apis/paths/auth_keylogin.py
openapi_client/apis/paths/auth_login.py
openapi_client/apis/paths/auth_logout.py
openapi_client/apis/paths/auth_request_trial.py
openapi_client/apis/paths/auth_resend_activation_mail.py
openapi_client/apis/paths/auth_reset_password.py
openapi_client/apis/paths/auth_send_reset_password_mail.py
openapi_client/apis/paths/auth_set_user_metadata.py
openapi_client/apis/paths/auth_signup.py
openapi_client/apis/paths/auth_start_trial.py
openapi_client/apis/paths/auth_who_am_i.py
openapi_client/apis/paths/dashboards_add_dashboard.py
openapi_client/apis/paths/dashboards_delete_dashboard.py
openapi_client/apis/paths/dashboards_get_dashboard.py
openapi_client/apis/paths/dashboards_get_dashlet_fields.py
openapi_client/apis/paths/dashboards_get_kibana_dashboards.py
openapi_client/apis/paths/dashboards_get_kibana_dashlet_fields.py
openapi_client/apis/paths/dashboards_get_project_dashboards.py
openapi_client/apis/paths/dashboards_update_dashboard.py
openapi_client/apis/paths/datasets_add_dataset.py
openapi_client/apis/paths/datasets_get_dataset_version.py
openapi_client/apis/paths/datasets_get_dataset_versions.py
openapi_client/apis/paths/datasets_get_datasets.py
openapi_client/apis/paths/datasets_get_latest_dataset_version.py
openapi_client/apis/paths/datasets_modify_dataset_version_note.py
openapi_client/apis/paths/datasets_parse_dataset.py
openapi_client/apis/paths/datasets_save_dataset_version.py
openapi_client/apis/paths/datasets_trash_dataset.py
openapi_client_tensorleap.egg-info/PKG-INFO
openapi_client_tensorleap.egg-info/SOURCES.txt
openapi_client_tensorleap.egg-info/dependency_links.txt
openapi_client_tensorleap.egg-info/requires.txt
openapi_client_tensorleap.egg-info/top_level.txt
