Metadata-Version: 2.1
Name: openapi-client-tensorleap
Version: 1.2.0.dev2
Summary: node-server
Home-page: 
Author: OpenAPI Generator community
Author-email: team@openapitools.org
License: SEE LICENSE IN LICENSE.md
Keywords: OpenAPI,OpenAPI-Generator,node-server
Requires-Python: >=3.7
